{
  "id": "318f4343-ffd9-4854-a094-beef906a15c3",
  "prevId": "00000000-0000-0000-0000-000000000000",
  "version": "7",
  "dialect": "postgresql",
  "tables": {
    "public.companies": {
      "name": "companies",
      "schema": "",
      "columns": {
        "id": {
          "name": "id",
          "type": "serial",
          "primaryKey": true,
          "notNull": true
        },
        "contact_id": {
          "name": "contact_id",
          "type": "integer",
          "primaryKey": false,
          "notNull": false
        },
        "name": {
          "name": "name",
          "type": "text",
          "primaryKey": false,
          "notNull": true
        },
        "short_name": {
          "name": "short_name",
          "type": "text",
          "primaryKey": false,
          "notNull": true
        },
        "business_entity": {
          "name": "business_entity",
          "type": "varchar(256)",
          "primaryKey": false,
          "notNull": true
        },
        "type": {
          "name": "type",
          "type": "text[]",
          "primaryKey": false,
          "notNull": true,
          "default": "'{}'::text[]"
        },
        "status": {
          "name": "status",
          "type": "company_status",
          "typeSchema": "public",
          "primaryKey": false,
          "notNull": false,
          "default": "'active'"
        },
        "created_at": {
          "name": "created_at",
          "type": "timestamp",
          "primaryKey": false,
          "notNull": true,
          "default": "now()"
        },
        "updated_at": {
          "name": "updated_at",
          "type": "timestamp",
          "primaryKey": false,
          "notNull": true,
          "default": "now()"
        },
        "address": {
          "name": "address",
          "type": "text",
          "primaryKey": false,
          "notNull": true,
          "default": "''"
        }
      },
      "indexes": {},
      "foreignKeys": {
        "companies_contact_id_contacts_id_fk": {
          "name": "companies_contact_id_contacts_id_fk",
          "tableFrom": "companies",
          "tableTo": "contacts",
          "columnsFrom": [
            "contact_id"
          ],
          "columnsTo": [
            "id"
          ],
          "onDelete": "no action",
          "onUpdate": "no action"
        }
      },
      "compositePrimaryKeys": {},
      "uniqueConstraints": {},
      "policies": {},
      "checkConstraints": {},
      "isRLSEnabled": false
    },
    "public.contacts": {
      "name": "contacts",
      "schema": "",
      "columns": {
        "id": {
          "name": "id",
          "type": "serial",
          "primaryKey": true,
          "notNull": true
        },
        "lastname": {
          "name": "lastname",
          "type": "varchar(256)",
          "primaryKey": false,
          "notNull": true
        },
        "firstname": {
          "name": "firstname",
          "type": "varchar(256)",
          "primaryKey": false,
          "notNull": true
        },
        "patronymic": {
          "name": "patronymic",
          "type": "varchar(256)",
          "primaryKey": false,
          "notNull": true,
          "default": "''"
        },
        "phone": {
          "name": "phone",
          "type": "varchar(256)",
          "primaryKey": false,
          "notNull": true
        },
        "email": {
          "name": "email",
          "type": "varchar(256)",
          "primaryKey": false,
          "notNull": true
        },
        "created_at": {
          "name": "created_at",
          "type": "timestamp",
          "primaryKey": false,
          "notNull": true,
          "default": "now()"
        },
        "updated_at": {
          "name": "updated_at",
          "type": "timestamp",
          "primaryKey": false,
          "notNull": true,
          "default": "now()"
        },
        "deleted": {
          "name": "deleted",
          "type": "boolean",
          "primaryKey": false,
          "notNull": true,
          "default": false
        }
      },
      "indexes": {},
      "foreignKeys": {},
      "compositePrimaryKeys": {},
      "uniqueConstraints": {
        "contacts_email_unique": {
          "name": "contacts_email_unique",
          "nullsNotDistinct": false,
          "columns": [
            "email"
          ]
        }
      },
      "policies": {},
      "checkConstraints": {},
      "isRLSEnabled": false
    },
    "public.contracts": {
      "name": "contracts",
      "schema": "",
      "columns": {
        "id": {
          "name": "id",
          "type": "serial",
          "primaryKey": true,
          "notNull": true
        },
        "no": {
          "name": "no",
          "type": "text",
          "primaryKey": false,
          "notNull": true
        },
        "company_id": {
          "name": "company_id",
          "type": "integer",
          "primaryKey": false,
          "notNull": false
        },
        "issue_date": {
          "name": "issue_date",
          "type": "timestamp",
          "primaryKey": false,
          "notNull": true
        }
      },
      "indexes": {},
      "foreignKeys": {
        "contracts_company_id_companies_id_fk": {
          "name": "contracts_company_id_companies_id_fk",
          "tableFrom": "contracts",
          "tableTo": "companies",
          "columnsFrom": [
            "company_id"
          ],
          "columnsTo": [
            "id"
          ],
          "onDelete": "no action",
          "onUpdate": "no action"
        }
      },
      "compositePrimaryKeys": {},
      "uniqueConstraints": {},
      "policies": {},
      "checkConstraints": {},
      "isRLSEnabled": false
    },
    "public.users": {
      "name": "users",
      "schema": "",
      "columns": {
        "id": {
          "name": "id",
          "type": "serial",
          "primaryKey": true,
          "notNull": true
        },
        "login": {
          "name": "login",
          "type": "varchar(256)",
          "primaryKey": false,
          "notNull": true
        },
        "password": {
          "name": "password",
          "type": "text",
          "primaryKey": false,
          "notNull": true
        },
        "created_at": {
          "name": "created_at",
          "type": "timestamp",
          "primaryKey": false,
          "notNull": true,
          "default": "now()"
        },
        "deleted": {
          "name": "deleted",
          "type": "boolean",
          "primaryKey": false,
          "notNull": true,
          "default": false
        }
      },
      "indexes": {},
      "foreignKeys": {},
      "compositePrimaryKeys": {},
      "uniqueConstraints": {
        "users_login_unique": {
          "name": "users_login_unique",
          "nullsNotDistinct": false,
          "columns": [
            "login"
          ]
        }
      },
      "policies": {},
      "checkConstraints": {},
      "isRLSEnabled": false
    },
    "public.photos": {
      "name": "photos",
      "schema": "",
      "columns": {
        "id": {
          "name": "id",
          "type": "serial",
          "primaryKey": true,
          "notNull": true
        },
        "company_id": {
          "name": "company_id",
          "type": "integer",
          "primaryKey": false,
          "notNull": false
        },
        "name": {
          "name": "name",
          "type": "text",
          "primaryKey": false,
          "notNull": true
        },
        "filepath": {
          "name": "filepath",
          "type": "text",
          "primaryKey": false,
          "notNull": true
        },
        "thumbpath": {
          "name": "thumbpath",
          "type": "text",
          "primaryKey": false,
          "notNull": true
        }
      },
      "indexes": {},
      "foreignKeys": {
        "photos_company_id_companies_id_fk": {
          "name": "photos_company_id_companies_id_fk",
          "tableFrom": "photos",
          "tableTo": "companies",
          "columnsFrom": [
            "company_id"
          ],
          "columnsTo": [
            "id"
          ],
          "onDelete": "no action",
          "onUpdate": "no action"
        }
      },
      "compositePrimaryKeys": {},
      "uniqueConstraints": {},
      "policies": {},
      "checkConstraints": {},
      "isRLSEnabled": false
    }
  },
  "enums": {},
  "schemas": {},
  "sequences": {},
  "roles": {},
  "policies": {},
  "views": {},
  "_meta": {
    "columns": {},
    "schemas": {},
    "tables": {}
  }
}